research_jupyter_templates/__init__.py
research_jupyter_templates/_version.py
research_jupyter_templates/research.ipynb
research_jupyter_templates-0.1.6.dist-info/LICENSE
research_jupyter_templates-0.1.6.dist-info/METADATA
research_jupyter_templates-0.1.6.dist-info/WHEEL
research_jupyter_templates-0.1.6.dist-info/top_level.txt
research_jupyter_templates-0.1.6.dist-info/RECORD
