Metadata-Version: 2.1
Name: research-jupyter-templates
Version: 0.1.6
Summary: I will here be experimenting with jupyter notebook templates, with a good structure that enforces good documentation and that can be used over and over again.
Home-page: https://github.com/martinlarsalbert/research_jupyter_templates
Maintainer: Martin Alexandersson
Maintainer-email: maa@sspa.se
License: MIT
Download-URL: https://github.com/martinlarsalbert/research_jupyter_templates
Requires-Dist: jupyterlab
Requires-Dist: jupyterlab-templates
